pulumi_remote_stack/__init__.py
pulumi_remote_stack/config.py
pulumi_remote_stack/provider.py
pulumi_remote_stack/remote_stack.py
pulumi_remote_stack/subprocess_run.py
pulumi_remote_stack-0.1.6.dist-info/LICENSE
pulumi_remote_stack-0.1.6.dist-info/METADATA
pulumi_remote_stack-0.1.6.dist-info/WHEEL
pulumi_remote_stack-0.1.6.dist-info/top_level.txt
pulumi_remote_stack-0.1.6.dist-info/RECORD
