Metadata-Version: 2.1
Name: pulumi-remote-stack
Version: 0.1.6
Summary: Pulumi Remote Stack
Home-page: https://github.com/pypa/pulumi-remote-stack
Author: Jan Češpivo
Author-email: developers@allusio.com
Project-URL: Bug Tracker, https://github.com/allusio/pulumi-remote-stack
Classifier: Programming Language :: Python :: 3
Classifier: License :: OSI Approved :: Apache Software License
Classifier: Operating System :: OS Independent
Requires-Python: >=3.6
License-File: LICENSE
